bestagents/__init__.py
bestagents/cli.py
bestagents/agents/base.py
bestagents/agents/runner.py
bestagents/agents/simple_openai_agent.py
bestagents/core/__init__.py
bestagents/core/base_protocol.py
bestagents/core/base_protocol_adapter.py
bestagents/core/client.py
bestagents/core/connector.py
bestagents/core/network.py
bestagents/core/system_commands.py
bestagents/launchers/__init__.py
bestagents/launchers/discovery_connector.py
bestagents/launchers/network_launcher.py
bestagents/launchers/terminal_console.py
bestagents/models/__init__.py
bestagents/models/manifest.py
bestagents/models/message_thread.py
bestagents/models/messages.py
bestagents/models/network_config.py
bestagents/models/network_profile.py
bestagents/models/tool.py
bestagents/protocols/__init__.py
bestagents/protocols/communication/__init__.py
bestagents/protocols/communication/simple_messaging/__init__.py
bestagents/protocols/communication/simple_messaging/adapter.py
bestagents/protocols/communication/simple_messaging/protocol.py
bestagents/protocols/communication/simple_messaging/protocol_manifest.json
bestagents/protocols/discovery/__init__.py
bestagents/protocols/discovery/agent_discovery/__init__.py
bestagents/protocols/discovery/agent_discovery/adapter.py
bestagents/protocols/discovery/agent_discovery/protocol.py
bestagents/protocols/discovery/agent_discovery/protocol_manifest.json
bestagents/utils/__init__.py
bestagents/utils/message_util.py
bestagents/utils/network_discovey.py
bestagents/utils/protocol_loaders.py
bestagents-0.4.0.dist-info/licenses/LICENSE
bestagents-0.4.0.dist-info/METADATA
bestagents-0.4.0.dist-info/WHEEL
bestagents-0.4.0.dist-info/entry_points.txt
bestagents-0.4.0.dist-info/top_level.txt
bestagents-0.4.0.dist-info/RECORD
