Metadata-Version: 2.4
Name: bestagents
Version: 0.4.0
Summary: A flexible framework for building multi-agent systems with customizable protocols
Home-page: https://github.com/bestagents/bestagents
Author: BestAgents Team
Author-email: BestAgents Team <info@bestagents.org>
License: Apache-2.0
Project-URL: Homepage, https://github.com/bestagents/bestagents
Project-URL: Documentation, https://bestagents.readthedocs.io
Project-URL: Repository, https://github.com/bestagents/bestagents
Project-URL: Issues, https://github.com/bestagents/bestagents/issues
Classifier: Development Status :: 3 - Alpha
Classifier: Intended Audience :: Developers
Classifier: License :: OSI Approved :: Apache Software License
Classifier: Programming Language :: Python :: 3
Classifier: Programming Language :: Python :: 3.7
Classifier: Programming Language :: Python :: 3.8
Classifier: Programming Language :: Python :: 3.9
Classifier: Programming Language :: Python :: 3.10
Classifier: Topic :: Software Development :: Libraries :: Python Modules
Requires-Python: >=3.7
License-File: LICENSE
Requires-Dist: pyyaml>=5.1
Requires-Dist: typing-extensions>=4.0.0
Requires-Dist: pydantic>=1.8.0
Requires-Dist: aiohttp>=3.8.0
Requires-Dist: jinja2>=3.0.0
Requires-Dist: websockets>=10.0
Dynamic: license-file
